MANIFEST.in
setup.py
django_report_scaffold.egg-info/PKG-INFO
django_report_scaffold.egg-info/SOURCES.txt
django_report_scaffold.egg-info/dependency_links.txt
django_report_scaffold.egg-info/requires.txt
django_report_scaffold.egg-info/top_level.txt
scaffold_report/__init__.py
scaffold_report/fields.py
scaffold_report/filters.py
scaffold_report/models.py
scaffold_report/report.py
scaffold_report/tests.py
scaffold_report/urls.py
scaffold_report/views.py
scaffold_report/static/scaffold_report/scaffold_report.css
scaffold_report/static/scaffold_report/scaffold_report.js
scaffold_report/static/scaffold_report/scaffold_report.js.orig
scaffold_report/templates/scaffold_report/base.html
scaffold_report/templates/scaffold_report/filter.html
scaffold_report/templates/scaffold_report/process_errors.html
scaffold_report/templates/scaffold_report/report.html
scaffold_report/templates/scaffold_report/report.html.orig
scaffold_report/templates/scaffold_report/table.html
scaffold_report/templates/scaffold_report/includes/header.html