Metadata-Version: 1.1
Name: django-report-scaffold
Version: 0.1.4
Summary: Create streamlined and flexible reporting tools for your end uesrs. Report scaffold is not a drop in application but a framework for creating reporting tools. Think of it like django admin.
Home-page: https://github.com/burke-software/django-report-scaffold
Author: David Burke
Author-email: david@burkesoftware.com
License: BSD
Keywords: django report
Platform: UNKNOWN
Classifier: Development Status :: 5 - Production/Stable
Classifier: Environment :: Web Environment
Classifier: Framework :: Django
Classifier: Programming Language :: Python
Classifier: Intended Audience :: Developers
Classifier: Intended Audience :: System Administrators
Classifier: License :: OSI Approved :: BSD License
